shellsy/__init__.py
shellsy/__main__.py
shellsy/exceptions.py
shellsy/help.py
shellsy/interpreter.py
shellsy/lang.py
shellsy/lexer.py
shellsy/plugin.py
shellsy/settings.py
shellsy/shell.py
shellsy/shellsy.py
shellsy/repl/__init__.py
shellsy-1.0.0.dist-info/LICENSE
shellsy-1.0.0.dist-info/METADATA
shellsy-1.0.0.dist-info/WHEEL
shellsy-1.0.0.dist-info/entry_points.txt
shellsy-1.0.0.dist-info/top_level.txt
shellsy-1.0.0.dist-info/RECORD
